ppf/constants/__init__.py
ppf/constants/constants.py
ppf_constants-0.5.dist-info/LICENSE
ppf_constants-0.5.dist-info/METADATA
ppf_constants-0.5.dist-info/WHEEL
ppf_constants-0.5.dist-info/top_level.txt
ppf_constants-0.5.dist-info/RECORD
