Metadata-Version: 2.1
Name: ppf-constants
Version: 0.5
Summary: physical constants and units
Author: Simon Zeller, Adrian Schlatter
License: BSD2
Project-URL: repository, https://github.com/adrianschlatter/ppf.constants/tree/master
Keywords: python,constants,units
Classifier: Development Status :: 5 - Production/Stable
Classifier: Topic :: Utilities
Classifier: License :: OSI Approved :: BSD License
Classifier: Programming Language :: Python
Classifier: Operating System :: OS Independent
License-File: LICENSE
Provides-Extra: dev
Requires-Dist: check-manifest ; extra == 'dev'
Requires-Dist: twine ; extra == 'dev'
Provides-Extra: test
Requires-Dist: pytest ; extra == 'test'
Requires-Dist: check-manifest ; extra == 'test'
Requires-Dist: flake8 ; extra == 'test'
Requires-Dist: flake8-pyproject ; extra == 'test'
Requires-Dist: coverage ; extra == 'test'
